esqlask/__init__.py
esqlask/enums.py
esqlask/generics.py
esqlask/manager.py
esqlask/mixins.py
esqlask/serializers.py
esqlask/viewsets.py
esqlask/bin/esqlask-admin.py
esqlask/conf/templates/app/models.py.template
esqlask/conf/templates/app/routes.py.template
esqlask/conf/templates/app/serializers.py.template
esqlask/conf/templates/app/viewsets.py.template
esqlask/conf/templates/project/dev.py.template
esqlask/conf/templates/project/server.py.template
esqlask/conf/templates/project/zappa_settings.json.template
esqlask/core/__init__.py
esqlask/core/management/__init__.py
esqlask/core/management/base.py
esqlask/core/management/commands/__init__.py
esqlask/core/management/commands/help.py
esqlask/core/management/commands/migrate.py
esqlask/core/management/commands/shell.py
esqlask/core/management/commands/startapp.py
esqlask/core/management/commands/startproject.py
esqlask/db/__init__.py
esqlask/db/models.py
esqlask-1.0.0.data/scripts/esqlask-admin.py
esqlask-1.0.0.data/scripts/teshu-admin.py
esqlask-1.0.0.dist-info/METADATA
esqlask-1.0.0.dist-info/RECORD
esqlask-1.0.0.dist-info/WHEEL
esqlask-1.0.0.dist-info/entry_points.txt
esqlask-1.0.0.dist-info/top_level.txt
teshu/__init__.py
teshu/enums.py
teshu/generics.py
teshu/manager.py
teshu/mixins.py
teshu/serializers.py
teshu/viewsets.py
teshu/bin/teshu-admin.py
teshu/conf/templates/app/models.py.template
teshu/conf/templates/app/routes.py.template
teshu/conf/templates/app/serializers.py.template
teshu/conf/templates/app/viewsets.py.template
teshu/conf/templates/project/dev.py.template
teshu/conf/templates/project/server.py.template
teshu/conf/templates/project/zappa_settings.json.template
teshu/core/__init__.py
teshu/core/management/__init__.py
teshu/core/management/base.py
teshu/core/management/commands/__init__.py
teshu/core/management/commands/help.py
teshu/core/management/commands/migrate.py
teshu/core/management/commands/shell.py
teshu/core/management/commands/startapp.py
teshu/core/management/commands/startproject.py
teshu/db/__init__.py
teshu/db/models.py
